redux/__init__.py
redux-0.1.0.dist-info/METADATA
redux-0.1.0.dist-info/RECORD
redux-0.1.0.dist-info/WHEEL
redux-0.1.0.dist-info/top_level.txt
