Metadata-Version: 2.1
Name: redux
Version: 0.1.0
Summary: Redux in Python
Home-page: https://github.com/kaelzhang/python-redux
Author: kaelzhang
Author-email: UNKNOWN
License: MIT
Keywords: redux
Platform: UNKNOWN
Classifier: Topic :: Software Development :: Libraries :: Python Modules
Classifier: Programming Language :: Python :: 3.7
Classifier: Programming Language :: Python :: 3.8
Classifier: Programming Language :: Python :: Implementation :: PyPy
Classifier: Topic :: Software Development :: Libraries :: Python Modules
Classifier: License :: OSI Approved :: MIT License
